triple_barrier/__init__.py
triple_barrier/constants.py
triple_barrier/orders.py
triple_barrier/plots.py
triple_barrier/trade_labeling.py
triple_barrier/trading.py
triple_barrier/types.py
triple_barrier-1.0.1.dist-info/METADATA
triple_barrier-1.0.1.dist-info/WHEEL
triple_barrier-1.0.1.dist-info/licenses/LICENSE
triple_barrier-1.0.1.dist-info/RECORD
