Metadata-Version: 2.3
Name: triple-barrier
Version: 1.0.1
Summary: Back-testing and machine learning pipelines trades labeling utility
Project-URL: Homepage, https://github.com/mchiuminatto/triple_barrier
Project-URL: Issues, https://github.com/mchiuminatto/triple_barrier/issues
Author-email: Marcello Chiuminatto <mch@thequantick.net>
Classifier: License :: OSI Approved :: MIT License
Classifier: Operating System :: OS Independent
Classifier: Programming Language :: Python :: 3
Requires-Python: >=3.11
Requires-Dist: matplotlib==3.8.2
Requires-Dist: mplfinance==0.12.10b0
Requires-Dist: pandas>=2.2
Requires-Dist: pyarrow>=16.0
Requires-Dist: pytest>=8
